DocumentInsightsGenerator/__init__.py
DocumentInsightsGenerator/documentinsightsgenerator.py
tests/__init__.py
tests/test_documentinsightsgenerator.py
DocumentInsightsGenerator-0.1.dist-info/LICENSE
DocumentInsightsGenerator-0.1.dist-info/METADATA
DocumentInsightsGenerator-0.1.dist-info/WHEEL
DocumentInsightsGenerator-0.1.dist-info/top_level.txt
DocumentInsightsGenerator-0.1.dist-info/RECORD
