Metadata-Version: 2.1
Name: DocumentInsightsGenerator
Version: 0.1
Summary: A package to generate comprehensive insights from documents using NLP techniques.
Home-page: https://github.com/pritiyadav888/DocumentInsightsGenerator
Author: Priti Yadav
Author-email: yadavpriti0210@gmail.com
License: MIT
Platform: UNKNOWN
Classifier: Development Status :: 3 - Alpha
Classifier: Intended Audience :: Developers
Classifier: License :: OSI Approved :: MIT License
Classifier: Programming Language :: Python :: 3.7
License-File: LICENSE
Requires-Dist: spacy
Requires-Dist: requests
Requires-Dist: transformers
Requires-Dist: scikit-learn
Requires-Dist: pdfplumber
Requires-Dist: pytesseract
Requires-Dist: pdfminer.six
Requires-Dist: Pillow
Requires-Dist: docx2txt
